{
	"entries" : 
	[
		{
			"name" : "CMAKE_BUILD_TYPE",
			"properties" : 
			[
				{
					"name" : "HELPSTRING",
					"value" : "Choose the type of build, options are: None Debug Release RelWithDebInfo MinSizeRel ..."
				}
			],
			"type" : "STRING",
			"value" : "Debug"
		},
		{
			"name" : "CMAKE_CACHEFILE_DIR",
			"properties" : 
			[
				{
					"name" : "HELPSTRING",
					"value" : "This is the directory where this CMakeCache.txt was created"
				}
			],
			"type" : "INTERNAL",
			"value" : "c:/Users/b6024306/source/Group Work/weird-golf-game/out/build/x64-Debug"
		},
		{
			"name" : "CMAKE_CACHE_MAJOR_VERSION",
			"properties" : 
			[
				{
					"name" : "HELPSTRING",
					"value" : "Major version of cmake used to create the current loaded cache"
				}
			],
			"type" : "INTERNAL",
			"value" : "3"
		},
		{
			"name" : "CMAKE_CACHE_MINOR_VERSION",
			"properties" : 
			[
				{
					"name" : "HELPSTRING",
					"value" : "Minor version of cmake used to create the current loaded cache"
				}
			],
			"type" : "INTERNAL",
			"value" : "14"
		},
		{
			"name" : "CMAKE_CACHE_PATCH_VERSION",
			"properties" : 
			[
				{
					"name" : "HELPSTRING",
					"value" : "Patch version of cmake used to create the current loaded cache"
				}
			],
			"type" : "INTERNAL",
			"value" : "19060802"
		},
		{
			"name" : "CMAKE_COMMAND",
			"properties" : 
			[
				{
					"name" : "HELPSTRING",
					"value" : "Path to CMake executable."
				}
			],
			"type" : "INTERNAL",
			"value" : "C:/Program Files (x86)/Microsoft Visual Studio/2019/Community/Common7/IDE/CommonExtensions/Microsoft/CMake/CMake/bin/cmake.exe"
		},
		{
			"name" : "CMAKE_CPACK_COMMAND",
			"properties" : 
			[
				{
					"name" : "HELPSTRING",
					"value" : "Path to cpack program executable."
				}
			],
			"type" : "INTERNAL",
			"value" : "C:/Program Files (x86)/Microsoft Visual Studio/2019/Community/Common7/IDE/CommonExtensions/Microsoft/CMake/CMake/bin/cpack.exe"
		},
		{
			"name" : "CMAKE_CTEST_COMMAND",
			"properties" : 
			[
				{
					"name" : "HELPSTRING",
					"value" : "Path to ctest program executable."
				}
			],
			"type" : "INTERNAL",
			"value" : "C:/Program Files (x86)/Microsoft Visual Studio/2019/Community/Common7/IDE/CommonExtensions/Microsoft/CMake/CMake/bin/ctest.exe"
		},
		{
			"name" : "CMAKE_CXX_COMPILER",
			"properties" : 
			[
				{
					"name" : "ADVANCED",
					"value" : "1"
				},
				{
					"name" : "HELPSTRING",
					"value" : "No help, variable specified on the command line."
				}
			],
			"type" : "FILEPATH",
			"value" : "C:/Program Files (x86)/Microsoft Visual Studio/2019/Community/VC/Tools/MSVC/14.22.27905/bin/HostX64/x64/cl.exe"
		},
		{
			"name" : "CMAKE_CXX_FLAGS",
			"properties" : 
			[
				{
					"name" : "ADVANCED",
					"value" : "1"
				},
				{
					"name" : "HELPSTRING",
					"value" : "Flags used by the CXX compiler during all build types."
				}
			],
			"type" : "STRING",
			"value" : "/DWIN32 /D_WINDOWS /W3 /GR /EHsc"
		},
		{
			"name" : "CMAKE_CXX_FLAGS_DEBUG",
			"properties" : 
			[
				{
					"name" : "ADVANCED",
					"value" : "1"
				},
				{
					"name" : "HELPSTRING",
					"value" : "Flags used by the CXX compiler during DEBUG builds."
				}
			],
			"type" : "STRING",
			"value" : "/MDd /ZI /Ob0 /Od /RTC1 /JMC"
		},
		{
			"name" : "CMAKE_CXX_FLAGS_MINSIZEREL",
			"properties" : 
			[
				{
					"name" : "ADVANCED",
					"value" : "1"
				},
				{
					"name" : "HELPSTRING",
					"value" : "Flags used by the CXX compiler during MINSIZEREL builds."
				}
			],
			"type" : "STRING",
			"value" : "/MD /O1 /Ob1 /DNDEBUG"
		},
		{
			"name" : "CMAKE_CXX_FLAGS_RELEASE",
			"properties" : 
			[
				{
					"name" : "ADVANCED",
					"value" : "1"
				},
				{
					"name" : "HELPSTRING",
					"value" : "Flags used by the CXX compiler during RELEASE builds."
				}
			],
			"type" : "STRING",
			"value" : "/MD /O2 /Ob2 /DNDEBUG"
		},
		{
			"name" : "CMAKE_CXX_FLAGS_RELWITHDEBINFO",
			"properties" : 
			[
				{
					"name" : "ADVANCED",
					"value" : "1"
				},
				{
					"name" : "HELPSTRING",
					"value" : "Flags used by the CXX compiler during RELWITHDEBINFO builds."
				}
			],
			"type" : "STRING",
			"value" : "/MD /Zi /O2 /Ob1 /DNDEBUG"
		},
		{
			"name" : "CMAKE_CXX_STANDARD_LIBRARIES",
			"properties" : 
			[
				{
					"name" : "ADVANCED",
					"value" : "1"
				},
				{
					"name" : "HELPSTRING",
					"value" : "Libraries linked by default with all C++ applications."
				}
			],
			"type" : "STRING",
			"value" : "kernel32.lib user32.lib gdi32.lib winspool.lib shell32.lib ole32.lib oleaut32.lib uuid.lib comdlg32.lib advapi32.lib"
		},
		{
			"name" : "CMAKE_C_COMPILER",
			"properties" : 
			[
				{
					"name" : "ADVANCED",
					"value" : "1"
				},
				{
					"name" : "HELPSTRING",
					"value" : "No help, variable specified on the command line."
				}
			],
			"type" : "FILEPATH",
			"value" : "C:/Program Files (x86)/Microsoft Visual Studio/2019/Community/VC/Tools/MSVC/14.22.27905/bin/HostX64/x64/cl.exe"
		},
		{
			"name" : "CMAKE_C_FLAGS",
			"properties" : 
			[
				{
					"name" : "ADVANCED",
					"value" : "1"
				},
				{
					"name" : "HELPSTRING",
					"value" : "Flags used by the C compiler during all build types."
				}
			],
			"type" : "STRING",
			"value" : "/DWIN32 /D_WINDOWS /W3"
		},
		{
			"name" : "CMAKE_C_FLAGS_DEBUG",
			"properties" : 
			[
				{
					"name" : "ADVANCED",
					"value" : "1"
				},
				{
					"name" : "HELPSTRING",
					"value" : "Flags used by the C compiler during DEBUG builds."
				}
			],
			"type" : "STRING",
			"value" : "/MDd /ZI /Ob0 /Od /RTC1 /JMC"
		},
		{
			"name" : "CMAKE_C_FLAGS_MINSIZEREL",
			"properties" : 
			[
				{
					"name" : "ADVANCED",
					"value" : "1"
				},
				{
					"name" : "HELPSTRING",
					"value" : "Flags used by the C compiler during MINSIZEREL builds."
				}
			],
			"type" : "STRING",
			"value" : "/MD /O1 /Ob1 /DNDEBUG"
		},
		{
			"name" : "CMAKE_C_FLAGS_RELEASE",
			"properties" : 
			[
				{
					"name" : "ADVANCED",
					"value" : "1"
				},
				{
					"name" : "HELPSTRING",
					"value" : "Flags used by the C compiler during RELEASE builds."
				}
			],
			"type" : "STRING",
			"value" : "/MD /O2 /Ob2 /DNDEBUG"
		},
		{
			"name" : "CMAKE_C_FLAGS_RELWITHDEBINFO",
			"properties" : 
			[
				{
					"name" : "ADVANCED",
					"value" : "1"
				},
				{
					"name" : "HELPSTRING",
					"value" : "Flags used by the C compiler during RELWITHDEBINFO builds."
				}
			],
			"type" : "STRING",
			"value" : "/MD /Zi /O2 /Ob1 /DNDEBUG"
		},
		{
			"name" : "CMAKE_C_STANDARD_LIBRARIES",
			"properties" : 
			[
				{
					"name" : "ADVANCED",
					"value" : "1"
				},
				{
					"name" : "HELPSTRING",
					"value" : "Libraries linked by default with all C applications."
				}
			],
			"type" : "STRING",
			"value" : "kernel32.lib user32.lib gdi32.lib winspool.lib shell32.lib ole32.lib oleaut32.lib uuid.lib comdlg32.lib advapi32.lib"
		},
		{
			"name" : "CMAKE_EXECUTABLE_FORMAT",
			"properties" : 
			[
				{
					"name" : "HELPSTRING",
					"value" : "Executable file format"
				}
			],
			"type" : "INTERNAL",
			"value" : "Unknown"
		},
		{
			"name" : "CMAKE_EXE_LINKER_FLAGS",
			"properties" : 
			[
				{
					"name" : "ADVANCED",
					"value" : "1"
				},
				{
					"name" : "HELPSTRING",
					"value" : "Flags used by the linker during all build types."
				}
			],
			"type" : "STRING",
			"value" : "/machine:x64"
		},
		{
			"name" : "CMAKE_EXE_LINKER_FLAGS_DEBUG",
			"properties" : 
			[
				{
					"name" : "ADVANCED",
					"value" : "1"
				},
				{
					"name" : "HELPSTRING",
					"value" : "Flags used by the linker during DEBUG builds."
				}
			],
			"type" : "STRING",
			"value" : "/debug /INCREMENTAL"
		},
		{
			"name" : "CMAKE_EXE_LINKER_FLAGS_MINSIZEREL",
			"properties" : 
			[
				{
					"name" : "ADVANCED",
					"value" : "1"
				},
				{
					"name" : "HELPSTRING",
					"value" : "Flags used by the linker during MINSIZEREL builds."
				}
			],
			"type" : "STRING",
			"value" : "/INCREMENTAL:NO"
		},
		{
			"name" : "CMAKE_EXE_LINKER_FLAGS_RELEASE",
			"properties" : 
			[
				{
					"name" : "ADVANCED",
					"value" : "1"
				},
				{
					"name" : "HELPSTRING",
					"value" : "Flags used by the linker during RELEASE builds."
				}
			],
			"type" : "STRING",
			"value" : "/INCREMENTAL:NO"
		},
		{
			"name" : "CMAKE_EXE_LINKER_FLAGS_RELWITHDEBINFO",
			"properties" : 
			[
				{
					"name" : "ADVANCED",
					"value" : "1"
				},
				{
					"name" : "HELPSTRING",
					"value" : "Flags used by the linker during RELWITHDEBINFO builds."
				}
			],
			"type" : "STRING",
			"value" : "/debug /INCREMENTAL"
		},
		{
			"name" : "CMAKE_EXPORT_COMPILE_COMMANDS",
			"properties" : 
			[
				{
					"name" : "ADVANCED",
					"value" : "1"
				},
				{
					"name" : "HELPSTRING",
					"value" : "Enable/Disable output of compile commands during generation."
				}
			],
			"type" : "BOOL",
			"value" : "OFF"
		},
		{
			"name" : "CMAKE_EXTRA_GENERATOR",
			"properties" : 
			[
				{
					"name" : "HELPSTRING",
					"value" : "Name of external makefile project generator."
				}
			],
			"type" : "INTERNAL",
			"value" : ""
		},
		{
			"name" : "CMAKE_GENERATOR",
			"properties" : 
			[
				{
					"name" : "HELPSTRING",
					"value" : "Name of generator."
				}
			],
			"type" : "INTERNAL",
			"value" : "Ninja"
		},
		{
			"name" : "CMAKE_GENERATOR_INSTANCE",
			"properties" : 
			[
				{
					"name" : "HELPSTRING",
					"value" : "Generator instance identifier."
				}
			],
			"type" : "INTERNAL",
			"value" : ""
		},
		{
			"name" : "CMAKE_GENERATOR_PLATFORM",
			"properties" : 
			[
				{
					"name" : "HELPSTRING",
					"value" : "Name of generator platform."
				}
			],
			"type" : "INTERNAL",
			"value" : ""
		},
		{
			"name" : "CMAKE_GENERATOR_TOOLSET",
			"properties" : 
			[
				{
					"name" : "HELPSTRING",
					"value" : "Name of generator toolset."
				}
			],
			"type" : "INTERNAL",
			"value" : ""
		},
		{
			"name" : "CMAKE_HAVE_PTHREAD_H",
			"properties" : 
			[
				{
					"name" : "HELPSTRING",
					"value" : "Have include pthread.h"
				}
			],
			"type" : "INTERNAL",
			"value" : ""
		},
		{
			"name" : "CMAKE_HOME_DIRECTORY",
			"properties" : 
			[
				{
					"name" : "HELPSTRING",
					"value" : "Source directory with the top level CMakeLists.txt file for this project"
				}
			],
			"type" : "INTERNAL",
			"value" : "C:/Users/b6024306/source/Group Work/weird-golf-game"
		},
		{
			"name" : "CMAKE_INSTALL_BINDIR",
			"properties" : 
			[
				{
					"name" : "ADVANCED",
					"value" : "1"
				},
				{
					"name" : "HELPSTRING",
					"value" : "User executables (bin)"
				}
			],
			"type" : "PATH",
			"value" : "bin"
		},
		{
			"name" : "CMAKE_INSTALL_DATADIR",
			"properties" : 
			[
				{
					"name" : "ADVANCED",
					"value" : "1"
				},
				{
					"name" : "HELPSTRING",
					"value" : "Read-only architecture-independent data (DATAROOTDIR)"
				}
			],
			"type" : "PATH",
			"value" : ""
		},
		{
			"name" : "CMAKE_INSTALL_DATAROOTDIR",
			"properties" : 
			[
				{
					"name" : "ADVANCED",
					"value" : "1"
				},
				{
					"name" : "HELPSTRING",
					"value" : "Read-only architecture-independent data root (share)"
				}
			],
			"type" : "PATH",
			"value" : "share"
		},
		{
			"name" : "CMAKE_INSTALL_DOCDIR",
			"properties" : 
			[
				{
					"name" : "ADVANCED",
					"value" : "1"
				},
				{
					"name" : "HELPSTRING",
					"value" : "Documentation root (DATAROOTDIR/doc/PROJECT_NAME)"
				}
			],
			"type" : "PATH",
			"value" : ""
		},
		{
			"name" : "CMAKE_INSTALL_INCLUDEDIR",
			"properties" : 
			[
				{
					"name" : "ADVANCED",
					"value" : "1"
				},
				{
					"name" : "HELPSTRING",
					"value" : "C header files (include)"
				}
			],
			"type" : "PATH",
			"value" : "include"
		},
		{
			"name" : "CMAKE_INSTALL_INFODIR",
			"properties" : 
			[
				{
					"name" : "ADVANCED",
					"value" : "1"
				},
				{
					"name" : "HELPSTRING",
					"value" : "Info documentation (DATAROOTDIR/info)"
				}
			],
			"type" : "PATH",
			"value" : ""
		},
		{
			"name" : "CMAKE_INSTALL_LIBDIR",
			"properties" : 
			[
				{
					"name" : "ADVANCED",
					"value" : "1"
				},
				{
					"name" : "HELPSTRING",
					"value" : "Object code libraries (lib)"
				}
			],
			"type" : "PATH",
			"value" : "lib"
		},
		{
			"name" : "CMAKE_INSTALL_LIBEXECDIR",
			"properties" : 
			[
				{
					"name" : "ADVANCED",
					"value" : "1"
				},
				{
					"name" : "HELPSTRING",
					"value" : "Program executables (libexec)"
				}
			],
			"type" : "PATH",
			"value" : "libexec"
		},
		{
			"name" : "CMAKE_INSTALL_LOCALEDIR",
			"properties" : 
			[
				{
					"name" : "ADVANCED",
					"value" : "1"
				},
				{
					"name" : "HELPSTRING",
					"value" : "Locale-dependent data (DATAROOTDIR/locale)"
				}
			],
			"type" : "PATH",
			"value" : ""
		},
		{
			"name" : "CMAKE_INSTALL_LOCALSTATEDIR",
			"properties" : 
			[
				{
					"name" : "ADVANCED",
					"value" : "1"
				},
				{
					"name" : "HELPSTRING",
					"value" : "Modifiable single-machine data (var)"
				}
			],
			"type" : "PATH",
			"value" : "var"
		},
		{
			"name" : "CMAKE_INSTALL_MANDIR",
			"properties" : 
			[
				{
					"name" : "ADVANCED",
					"value" : "1"
				},
				{
					"name" : "HELPSTRING",
					"value" : "Man documentation (DATAROOTDIR/man)"
				}
			],
			"type" : "PATH",
			"value" : ""
		},
		{
			"name" : "CMAKE_INSTALL_OLDINCLUDEDIR",
			"properties" : 
			[
				{
					"name" : "ADVANCED",
					"value" : "1"
				},
				{
					"name" : "HELPSTRING",
					"value" : "C header files for non-gcc (/usr/include)"
				}
			],
			"type" : "PATH",
			"value" : "/usr/include"
		},
		{
			"name" : "CMAKE_INSTALL_PREFIX",
			"properties" : 
			[
				{
					"name" : "HELPSTRING",
					"value" : "No help, variable specified on the command line."
				}
			],
			"type" : "PATH",
			"value" : "C:/Users/b6024306/source/Group Work/weird-golf-game/out/install/x64-Debug"
		},
		{
			"name" : "CMAKE_INSTALL_RUNSTATEDIR",
			"properties" : 
			[
				{
					"name" : "ADVANCED",
					"value" : "1"
				},
				{
					"name" : "HELPSTRING",
					"value" : "Run-time variable data (LOCALSTATEDIR/run)"
				}
			],
			"type" : "PATH",
			"value" : ""
		},
		{
			"name" : "CMAKE_INSTALL_SBINDIR",
			"properties" : 
			[
				{
					"name" : "ADVANCED",
					"value" : "1"
				},
				{
					"name" : "HELPSTRING",
					"value" : "System admin executables (sbin)"
				}
			],
			"type" : "PATH",
			"value" : "sbin"
		},
		{
			"name" : "CMAKE_INSTALL_SHAREDSTATEDIR",
			"properties" : 
			[
				{
					"name" : "ADVANCED",
					"value" : "1"
				},
				{
					"name" : "HELPSTRING",
					"value" : "Modifiable architecture-independent data (com)"
				}
			],
			"type" : "PATH",
			"value" : "com"
		},
		{
			"name" : "CMAKE_INSTALL_SYSCONFDIR",
			"properties" : 
			[
				{
					"name" : "ADVANCED",
					"value" : "1"
				},
				{
					"name" : "HELPSTRING",
					"value" : "Read-only single-machine data (etc)"
				}
			],
			"type" : "PATH",
			"value" : "etc"
		},
		{
			"name" : "CMAKE_LINKER",
			"properties" : 
			[
				{
					"name" : "ADVANCED",
					"value" : "1"
				},
				{
					"name" : "HELPSTRING",
					"value" : "Path to a program."
				}
			],
			"type" : "FILEPATH",
			"value" : "C:/Program Files (x86)/Microsoft Visual Studio/2019/Community/VC/Tools/MSVC/14.22.27905/bin/Hostx64/x64/link.exe"
		},
		{
			"name" : "CMAKE_MAKE_PROGRAM",
			"properties" : 
			[
				{
					"name" : "HELPSTRING",
					"value" : "make program"
				}
			],
			"type" : "FILEPATH",
			"value" : "C:/Program Files (x86)/Microsoft Visual Studio/2019/Community/Common7/IDE/CommonExtensions/Microsoft/CMake/Ninja/ninja.exe"
		},
		{
			"name" : "CMAKE_MODULE_LINKER_FLAGS",
			"properties" : 
			[
				{
					"name" : "ADVANCED",
					"value" : "1"
				},
				{
					"name" : "HELPSTRING",
					"value" : "Flags used by the linker during the creation of modules during all build types."
				}
			],
			"type" : "STRING",
			"value" : "/machine:x64"
		},
		{
			"name" : "CMAKE_MODULE_LINKER_FLAGS_DEBUG",
			"properties" : 
			[
				{
					"name" : "ADVANCED",
					"value" : "1"
				},
				{
					"name" : "HELPSTRING",
					"value" : "Flags used by the linker during the creation of modules during DEBUG builds."
				}
			],
			"type" : "STRING",
			"value" : "/debug /INCREMENTAL"
		},
		{
			"name" : "CMAKE_MODULE_LINKER_FLAGS_MINSIZEREL",
			"properties" : 
			[
				{
					"name" : "ADVANCED",
					"value" : "1"
				},
				{
					"name" : "HELPSTRING",
					"value" : "Flags used by the linker during the creation of modules during MINSIZEREL builds."
				}
			],
			"type" : "STRING",
			"value" : "/INCREMENTAL:NO"
		},
		{
			"name" : "CMAKE_MODULE_LINKER_FLAGS_RELEASE",
			"properties" : 
			[
				{
					"name" : "ADVANCED",
					"value" : "1"
				},
				{
					"name" : "HELPSTRING",
					"value" : "Flags used by the linker during the creation of modules during RELEASE builds."
				}
			],
			"type" : "STRING",
			"value" : "/INCREMENTAL:NO"
		},
		{
			"name" : "CMAKE_MODULE_LINKER_FLAGS_RELWITHDEBINFO",
			"properties" : 
			[
				{
					"name" : "ADVANCED",
					"value" : "1"
				},
				{
					"name" : "HELPSTRING",
					"value" : "Flags used by the linker during the creation of modules during RELWITHDEBINFO builds."
				}
			],
			"type" : "STRING",
			"value" : "/debug /INCREMENTAL"
		},
		{
			"name" : "CMAKE_MT",
			"properties" : 
			[
				{
					"name" : "ADVANCED",
					"value" : "1"
				},
				{
					"name" : "HELPSTRING",
					"value" : "Path to a program."
				}
			],
			"type" : "FILEPATH",
			"value" : "C:/Program Files (x86)/Windows Kits/10/bin/10.0.18362.0/x64/mt.exe"
		},
		{
			"name" : "CMAKE_NUMBER_OF_MAKEFILES",
			"properties" : 
			[
				{
					"name" : "HELPSTRING",
					"value" : "number of local generators"
				}
			],
			"type" : "INTERNAL",
			"value" : "5"
		},
		{
			"name" : "CMAKE_PLATFORM_INFO_INITIALIZED",
			"properties" : 
			[
				{
					"name" : "HELPSTRING",
					"value" : "Platform information initialized"
				}
			],
			"type" : "INTERNAL",
			"value" : "1"
		},
		{
			"name" : "CMAKE_PROJECT_DESCRIPTION",
			"properties" : 
			[
				{
					"name" : "HELPSTRING",
					"value" : "Value Computed by CMake"
				}
			],
			"type" : "STATIC",
			"value" : ""
		},
		{
			"name" : "CMAKE_PROJECT_HOMEPAGE_URL",
			"properties" : 
			[
				{
					"name" : "HELPSTRING",
					"value" : "Value Computed by CMake"
				}
			],
			"type" : "STATIC",
			"value" : ""
		},
		{
			"name" : "CMAKE_PROJECT_NAME",
			"properties" : 
			[
				{
					"name" : "HELPSTRING",
					"value" : "Value Computed by CMake"
				}
			],
			"type" : "STATIC",
			"value" : "weird_golf_game"
		},
		{
			"name" : "CMAKE_PROJECT_VERSION",
			"properties" : 
			[
				{
					"name" : "HELPSTRING",
					"value" : "Value Computed by CMake"
				}
			],
			"type" : "STATIC",
			"value" : "1.5.0"
		},
		{
			"name" : "CMAKE_PROJECT_VERSION_MAJOR",
			"properties" : 
			[
				{
					"name" : "HELPSTRING",
					"value" : "Value Computed by CMake"
				}
			],
			"type" : "STATIC",
			"value" : "1"
		},
		{
			"name" : "CMAKE_PROJECT_VERSION_MINOR",
			"properties" : 
			[
				{
					"name" : "HELPSTRING",
					"value" : "Value Computed by CMake"
				}
			],
			"type" : "STATIC",
			"value" : "5"
		},
		{
			"name" : "CMAKE_PROJECT_VERSION_PATCH",
			"properties" : 
			[
				{
					"name" : "HELPSTRING",
					"value" : "Value Computed by CMake"
				}
			],
			"type" : "STATIC",
			"value" : "0"
		},
		{
			"name" : "CMAKE_PROJECT_VERSION_TWEAK",
			"properties" : 
			[
				{
					"name" : "HELPSTRING",
					"value" : "Value Computed by CMake"
				}
			],
			"type" : "STATIC",
			"value" : ""
		},
		{
			"name" : "CMAKE_RC_COMPILER",
			"properties" : 
			[
				{
					"name" : "ADVANCED",
					"value" : "1"
				},
				{
					"name" : "HELPSTRING",
					"value" : "RC compiler"
				}
			],
			"type" : "FILEPATH",
			"value" : "C:/Program Files (x86)/Windows Kits/10/bin/10.0.18362.0/x64/rc.exe"
		},
		{
			"name" : "CMAKE_RC_COMPILER_WORKS",
			"properties" : 
			[
				{
					"name" : "HELPSTRING",
					"value" : ""
				}
			],
			"type" : "INTERNAL",
			"value" : "1"
		},
		{
			"name" : "CMAKE_RC_FLAGS",
			"properties" : 
			[
				{
					"name" : "ADVANCED",
					"value" : "1"
				},
				{
					"name" : "HELPSTRING",
					"value" : "Flags for Windows Resource Compiler during all build types."
				}
			],
			"type" : "STRING",
			"value" : "/DWIN32"
		},
		{
			"name" : "CMAKE_RC_FLAGS_DEBUG",
			"properties" : 
			[
				{
					"name" : "ADVANCED",
					"value" : "1"
				},
				{
					"name" : "HELPSTRING",
					"value" : "Flags for Windows Resource Compiler during DEBUG builds."
				}
			],
			"type" : "STRING",
			"value" : "/D_DEBUG"
		},
		{
			"name" : "CMAKE_RC_FLAGS_MINSIZEREL",
			"properties" : 
			[
				{
					"name" : "ADVANCED",
					"value" : "1"
				},
				{
					"name" : "HELPSTRING",
					"value" : "Flags for Windows Resource Compiler during MINSIZEREL builds."
				}
			],
			"type" : "STRING",
			"value" : ""
		},
		{
			"name" : "CMAKE_RC_FLAGS_RELEASE",
			"properties" : 
			[
				{
					"name" : "ADVANCED",
					"value" : "1"
				},
				{
					"name" : "HELPSTRING",
					"value" : "Flags for Windows Resource Compiler during RELEASE builds."
				}
			],
			"type" : "STRING",
			"value" : ""
		},
		{
			"name" : "CMAKE_RC_FLAGS_RELWITHDEBINFO",
			"properties" : 
			[
				{
					"name" : "ADVANCED",
					"value" : "1"
				},
				{
					"name" : "HELPSTRING",
					"value" : "Flags for Windows Resource Compiler during RELWITHDEBINFO builds."
				}
			],
			"type" : "STRING",
			"value" : ""
		},
		{
			"name" : "CMAKE_ROOT",
			"properties" : 
			[
				{
					"name" : "HELPSTRING",
					"value" : "Path to CMake installation."
				}
			],
			"type" : "INTERNAL",
			"value" : "C:/Program Files (x86)/Microsoft Visual Studio/2019/Community/Common7/IDE/CommonExtensions/Microsoft/CMake/CMake/share/cmake-3.14"
		},
		{
			"name" : "CMAKE_SHARED_LINKER_FLAGS",
			"properties" : 
			[
				{
					"name" : "ADVANCED",
					"value" : "1"
				},
				{
					"name" : "HELPSTRING",
					"value" : "Flags used by the linker during the creation of shared libraries during all build types."
				}
			],
			"type" : "STRING",
			"value" : "/machine:x64"
		},
		{
			"name" : "CMAKE_SHARED_LINKER_FLAGS_DEBUG",
			"properties" : 
			[
				{
					"name" : "ADVANCED",
					"value" : "1"
				},
				{
					"name" : "HELPSTRING",
					"value" : "Flags used by the linker during the creation of shared libraries during DEBUG builds."
				}
			],
			"type" : "STRING",
			"value" : "/debug /INCREMENTAL"
		},
		{
			"name" : "CMAKE_SHARED_LINKER_FLAGS_MINSIZEREL",
			"properties" : 
			[
				{
					"name" : "ADVANCED",
					"value" : "1"
				},
				{
					"name" : "HELPSTRING",
					"value" : "Flags used by the linker during the creation of shared libraries during MINSIZEREL builds."
				}
			],
			"type" : "STRING",
			"value" : "/INCREMENTAL:NO"
		},
		{
			"name" : "CMAKE_SHARED_LINKER_FLAGS_RELEASE",
			"properties" : 
			[
				{
					"name" : "ADVANCED",
					"value" : "1"
				},
				{
					"name" : "HELPSTRING",
					"value" : "Flags used by the linker during the creation of shared libraries during RELEASE builds."
				}
			],
			"type" : "STRING",
			"value" : "/INCREMENTAL:NO"
		},
		{
			"name" : "CMAKE_SHARED_LINKER_FLAGS_RELWITHDEBINFO",
			"properties" : 
			[
				{
					"name" : "ADVANCED",
					"value" : "1"
				},
				{
					"name" : "HELPSTRING",
					"value" : "Flags used by the linker during the creation of shared libraries during RELWITHDEBINFO builds."
				}
			],
			"type" : "STRING",
			"value" : "/debug /INCREMENTAL"
		},
		{
			"name" : "CMAKE_SKIP_INSTALL_RPATH",
			"properties" : 
			[
				{
					"name" : "ADVANCED",
					"value" : "1"
				},
				{
					"name" : "HELPSTRING",
					"value" : "If set, runtime paths are not added when installing shared libraries, but are added when building."
				}
			],
			"type" : "BOOL",
			"value" : "NO"
		},
		{
			"name" : "CMAKE_SKIP_RPATH",
			"properties" : 
			[
				{
					"name" : "ADVANCED",
					"value" : "1"
				},
				{
					"name" : "HELPSTRING",
					"value" : "If set, runtime paths are not added when using shared libraries."
				}
			],
			"type" : "BOOL",
			"value" : "NO"
		},
		{
			"name" : "CMAKE_STATIC_LINKER_FLAGS",
			"properties" : 
			[
				{
					"name" : "ADVANCED",
					"value" : "1"
				},
				{
					"name" : "HELPSTRING",
					"value" : "Flags used by the linker during the creation of static libraries during all build types."
				}
			],
			"type" : "STRING",
			"value" : "/machine:x64"
		},
		{
			"name" : "CMAKE_STATIC_LINKER_FLAGS_DEBUG",
			"properties" : 
			[
				{
					"name" : "ADVANCED",
					"value" : "1"
				},
				{
					"name" : "HELPSTRING",
					"value" : "Flags used by the linker during the creation of static libraries during DEBUG builds."
				}
			],
			"type" : "STRING",
			"value" : ""
		},
		{
			"name" : "CMAKE_STATIC_LINKER_FLAGS_MINSIZEREL",
			"properties" : 
			[
				{
					"name" : "ADVANCED",
					"value" : "1"
				},
				{
					"name" : "HELPSTRING",
					"value" : "Flags used by the linker during the creation of static libraries during MINSIZEREL builds."
				}
			],
			"type" : "STRING",
			"value" : ""
		},
		{
			"name" : "CMAKE_STATIC_LINKER_FLAGS_RELEASE",
			"properties" : 
			[
				{
					"name" : "ADVANCED",
					"value" : "1"
				},
				{
					"name" : "HELPSTRING",
					"value" : "Flags used by the linker during the creation of static libraries during RELEASE builds."
				}
			],
			"type" : "STRING",
			"value" : ""
		},
		{
			"name" : "CMAKE_STATIC_LINKER_FLAGS_RELWITHDEBINFO",
			"properties" : 
			[
				{
					"name" : "ADVANCED",
					"value" : "1"
				},
				{
					"name" : "HELPSTRING",
					"value" : "Flags used by the linker during the creation of static libraries during RELWITHDEBINFO builds."
				}
			],
			"type" : "STRING",
			"value" : ""
		},
		{
			"name" : "CMAKE_VERBOSE_MAKEFILE",
			"properties" : 
			[
				{
					"name" : "ADVANCED",
					"value" : "1"
				},
				{
					"name" : "HELPSTRING",
					"value" : "If this value is on, makefiles will be generated without the .SILENT directive, and all commands will be echoed to the console during the make.  This is useful for debugging only. With Visual Studio IDE projects all commands are done without /nologo."
				}
			],
			"type" : "BOOL",
			"value" : "FALSE"
		},
		{
			"name" : "FIND_PACKAGE_MESSAGE_DETAILS_OpenGL",
			"properties" : 
			[
				{
					"name" : "HELPSTRING",
					"value" : "Details about finding OpenGL"
				}
			],
			"type" : "INTERNAL",
			"value" : "[opengl32][c ][v()]"
		},
		{
			"name" : "FIND_PACKAGE_MESSAGE_DETAILS_Threads",
			"properties" : 
			[
				{
					"name" : "HELPSTRING",
					"value" : "Details about finding Threads"
				}
			],
			"type" : "INTERNAL",
			"value" : "[TRUE][v()]"
		},
		{
			"name" : "GPU_DLL_COPIED",
			"properties" : 
			[
				{
					"name" : "HELPSTRING",
					"value" : "PhysX GPU dlls copied"
				}
			],
			"type" : "INTERNAL",
			"value" : "1"
		},
		{
			"name" : "HAS_FCNTL",
			"properties" : 
			[
				{
					"name" : "HELPSTRING",
					"value" : "Have function fcntl"
				}
			],
			"type" : "INTERNAL",
			"value" : ""
		},
		{
			"name" : "HAS_GETADDRINFO",
			"properties" : 
			[
				{
					"name" : "HELPSTRING",
					"value" : "Have function getaddrinfo"
				}
			],
			"type" : "INTERNAL",
			"value" : ""
		},
		{
			"name" : "HAS_GETHOSTBYADDR_R",
			"properties" : 
			[
				{
					"name" : "HELPSTRING",
					"value" : "Have function gethostbyaddr_r"
				}
			],
			"type" : "INTERNAL",
			"value" : ""
		},
		{
			"name" : "HAS_GETHOSTBYNAME_R",
			"properties" : 
			[
				{
					"name" : "HELPSTRING",
					"value" : "Have function gethostbyname_r"
				}
			],
			"type" : "INTERNAL",
			"value" : ""
		},
		{
			"name" : "HAS_GETNAMEINFO",
			"properties" : 
			[
				{
					"name" : "HELPSTRING",
					"value" : "Have function getnameinfo"
				}
			],
			"type" : "INTERNAL",
			"value" : ""
		},
		{
			"name" : "HAS_INET_NTOP",
			"properties" : 
			[
				{
					"name" : "HELPSTRING",
					"value" : "Have function inet_ntop"
				}
			],
			"type" : "INTERNAL",
			"value" : ""
		},
		{
			"name" : "HAS_INET_PTON",
			"properties" : 
			[
				{
					"name" : "HELPSTRING",
					"value" : "Have function inet_pton"
				}
			],
			"type" : "INTERNAL",
			"value" : ""
		},
		{
			"name" : "HAS_MSGHDR_FLAGS",
			"properties" : 
			[
				{
					"name" : "HELPSTRING",
					"value" : "Test HAS_MSGHDR_FLAGS"
				}
			],
			"type" : "INTERNAL",
			"value" : ""
		},
		{
			"name" : "HAS_POLL",
			"properties" : 
			[
				{
					"name" : "HELPSTRING",
					"value" : "Have function poll"
				}
			],
			"type" : "INTERNAL",
			"value" : ""
		},
		{
			"name" : "HAS_SOCKLEN_T",
			"properties" : 
			[
				{
					"name" : "HELPSTRING",
					"value" : "CHECK_TYPE_SIZE: socklen_t unknown"
				}
			],
			"type" : "INTERNAL",
			"value" : ""
		},
		{
			"name" : "HAVE_HAS_SOCKLEN_T",
			"properties" : 
			[
				{
					"name" : "HELPSTRING",
					"value" : "Result of TRY_COMPILE"
				}
			],
			"type" : "INTERNAL",
			"value" : "FALSE"
		},
		{
			"name" : "NV_APPEND_CONFIG_NAME",
			"properties" : 
			[
				{
					"name" : "HELPSTRING",
					"value" : "Append config (DEBUG, CHECKED, PROFILE or '' for release) to outputted binaries."
				}
			],
			"type" : "BOOL",
			"value" : "OFF"
		},
		{
			"name" : "NV_FORCE_32BIT_SUFFIX",
			"properties" : 
			[
				{
					"name" : "HELPSTRING",
					"value" : "Force a 32 bit suffix for platforms that don't register properly."
				}
			],
			"type" : "BOOL",
			"value" : "OFF"
		},
		{
			"name" : "NV_FORCE_64BIT_SUFFIX",
			"properties" : 
			[
				{
					"name" : "HELPSTRING",
					"value" : "Force a 64 bit suffix for platforms that don't register properly."
				}
			],
			"type" : "BOOL",
			"value" : "OFF"
		},
		{
			"name" : "NV_USE_DEBUG_WINCRT",
			"properties" : 
			[
				{
					"name" : "HELPSTRING",
					"value" : "Use the debug version of the CRT"
				}
			],
			"type" : "BOOL",
			"value" : "ON"
		},
		{
			"name" : "NV_USE_GAMEWORKS_OUTPUT_DIRS",
			"properties" : 
			[
				{
					"name" : "HELPSTRING",
					"value" : "Use new GameWorks folder structure for binary output."
				}
			],
			"type" : "BOOL",
			"value" : "ON"
		},
		{
			"name" : "NV_USE_STATIC_WINCRT",
			"properties" : 
			[
				{
					"name" : "HELPSTRING",
					"value" : "Use the statically linked windows CRT"
				}
			],
			"type" : "BOOL",
			"value" : "OFF"
		},
		{
			"name" : "OPENGL_EGL_INCLUDE_DIR",
			"properties" : 
			[
				{
					"name" : "ADVANCED",
					"value" : "1"
				},
				{
					"name" : "HELPSTRING",
					"value" : "(This variable does not exist and should not be used)"
				}
			],
			"type" : "UNINITIALIZED",
			"value" : ""
		},
		{
			"name" : "OPENGL_GLX_INCLUDE_DIR",
			"properties" : 
			[
				{
					"name" : "ADVANCED",
					"value" : "1"
				},
				{
					"name" : "HELPSTRING",
					"value" : "(This variable does not exist and should not be used)"
				}
			],
			"type" : "UNINITIALIZED",
			"value" : ""
		},
		{
			"name" : "OPENGL_INCLUDE_DIR",
			"properties" : 
			[
				{
					"name" : "ADVANCED",
					"value" : "1"
				},
				{
					"name" : "HELPSTRING",
					"value" : "(This variable does not exist and should not be used)"
				}
			],
			"type" : "UNINITIALIZED",
			"value" : ""
		},
		{
			"name" : "OPENGL_egl_LIBRARY",
			"properties" : 
			[
				{
					"name" : "ADVANCED",
					"value" : "1"
				},
				{
					"name" : "HELPSTRING",
					"value" : "(This variable does not exist and should not be used)"
				}
			],
			"type" : "UNINITIALIZED",
			"value" : ""
		},
		{
			"name" : "OPENGL_gl_LIBRARY",
			"properties" : 
			[
				{
					"name" : "ADVANCED",
					"value" : "1"
				},
				{
					"name" : "HELPSTRING",
					"value" : "OpenGL library for win32"
				}
			],
			"type" : "STRING",
			"value" : "opengl32"
		},
		{
			"name" : "OPENGL_glu_LIBRARY",
			"properties" : 
			[
				{
					"name" : "ADVANCED",
					"value" : "1"
				},
				{
					"name" : "HELPSTRING",
					"value" : "GLU library for win32"
				}
			],
			"type" : "STRING",
			"value" : "glu32"
		},
		{
			"name" : "OPENGL_glx_LIBRARY",
			"properties" : 
			[
				{
					"name" : "ADVANCED",
					"value" : "1"
				},
				{
					"name" : "HELPSTRING",
					"value" : "(This variable does not exist and should not be used)"
				}
			],
			"type" : "UNINITIALIZED",
			"value" : ""
		},
		{
			"name" : "OPENGL_opengl_LIBRARY",
			"properties" : 
			[
				{
					"name" : "ADVANCED",
					"value" : "1"
				},
				{
					"name" : "HELPSTRING",
					"value" : "(This variable does not exist and should not be used)"
				}
			],
			"type" : "UNINITIALIZED",
			"value" : ""
		},
		{
			"name" : "OPENGL_xmesa_INCLUDE_DIR",
			"properties" : 
			[
				{
					"name" : "ADVANCED",
					"value" : "1"
				},
				{
					"name" : "HELPSTRING",
					"value" : "(This variable does not exist and should not be used)"
				}
			],
			"type" : "UNINITIALIZED",
			"value" : ""
		},
		{
			"name" : "PHYSX_CXX_FLAGS",
			"properties" : 
			[
				{
					"name" : "HELPSTRING",
					"value" : "PhysX CXX"
				}
			],
			"type" : "INTERNAL",
			"value" : "/d2Zi+ /MP /WX /W4 /GF /GS- /GR- /Gd /fp:fast /Oy /wd4514 /wd4820 /wd4127 /wd4710 /wd4711 /wd4577 /wd4996"
		},
		{
			"name" : "PHYSX_CXX_FLAGS_CHECKED",
			"properties" : 
			[
				{
					"name" : "HELPSTRING",
					"value" : "PhysX Checked CXX Flags"
				}
			],
			"type" : "INTERNAL",
			"value" : "/Ox /MD /D \"_HAS_ITERATOR_DEBUGGING=0\" /D \"_ITERATOR_DEBUG_LEVEL=0\" /D \"NDEBUG\" /Zi"
		},
		{
			"name" : "PHYSX_CXX_FLAGS_DEBUG",
			"properties" : 
			[
				{
					"name" : "HELPSTRING",
					"value" : "PhysX Debug CXX Flags"
				}
			],
			"type" : "INTERNAL",
			"value" : "/Od /MDd /D \"_DEBUG\" /RTCu /Zi"
		},
		{
			"name" : "PHYSX_CXX_FLAGS_PROFILE",
			"properties" : 
			[
				{
					"name" : "HELPSTRING",
					"value" : "PhysX Profile CXX Flags"
				}
			],
			"type" : "INTERNAL",
			"value" : "/Ox /MD /D \"_HAS_ITERATOR_DEBUGGING=0\" /D \"_ITERATOR_DEBUG_LEVEL=0\" /D \"NDEBUG\" /Zi"
		},
		{
			"name" : "PHYSX_CXX_FLAGS_RELEASE",
			"properties" : 
			[
				{
					"name" : "HELPSTRING",
					"value" : "PhysX Release CXX Flags"
				}
			],
			"type" : "INTERNAL",
			"value" : "/Ox /MD /D \"_HAS_ITERATOR_DEBUGGING=0\" /D \"_ITERATOR_DEBUG_LEVEL=0\" /D \"NDEBUG\" /Zi"
		},
		{
			"name" : "PHYSX_WINDOWS_CHECKED_COMPILE_DEFS",
			"properties" : 
			[
				{
					"name" : "HELPSTRING",
					"value" : "Checked PhysX preprocessor definitions"
				}
			],
			"type" : "INTERNAL",
			"value" : "PX_CHECKED=1;PX_NVTX=0;PX_SUPPORT_PVD=1"
		},
		{
			"name" : "PHYSX_WINDOWS_COMPILE_DEFS",
			"properties" : 
			[
				{
					"name" : "HELPSTRING",
					"value" : "Base PhysX preprocessor definitions"
				}
			],
			"type" : "INTERNAL",
			"value" : "WIN32;WIN64;;;_CRT_SECURE_NO_DEPRECATE;_CRT_NONSTDC_NO_DEPRECATE;_WINSOCK_DEPRECATED_NO_WARNINGS;"
		},
		{
			"name" : "PHYSX_WINDOWS_DEBUG_COMPILE_DEFS",
			"properties" : 
			[
				{
					"name" : "HELPSTRING",
					"value" : "Debug PhysX preprocessor definitions"
				}
			],
			"type" : "INTERNAL",
			"value" : "PX_DEBUG=1;PX_CHECKED=1;PX_NVTX=0;PX_SUPPORT_PVD=1"
		},
		{
			"name" : "PHYSX_WINDOWS_PROFILE_COMPILE_DEFS",
			"properties" : 
			[
				{
					"name" : "HELPSTRING",
					"value" : "Profile PhysX preprocessor definitions"
				}
			],
			"type" : "INTERNAL",
			"value" : "PX_PROFILE=1;PX_NVTX=0;PX_SUPPORT_PVD=1"
		},
		{
			"name" : "PHYSX_WINDOWS_RELEASE_COMPILE_DEFS",
			"properties" : 
			[
				{
					"name" : "HELPSTRING",
					"value" : "Release PhysX preprocessor definitions"
				}
			],
			"type" : "INTERNAL",
			"value" : "PX_SUPPORT_PVD=0"
		},
		{
			"name" : "PX_BUILDPUBLICSAMPLES",
			"properties" : 
			[
				{
					"name" : "HELPSTRING",
					"value" : "Generate the samples"
				}
			],
			"type" : "BOOL",
			"value" : "OFF"
		},
		{
			"name" : "PX_BUILDSNIPPETS",
			"properties" : 
			[
				{
					"name" : "HELPSTRING",
					"value" : "Generate the snippets"
				}
			],
			"type" : "BOOL",
			"value" : "OFF"
		},
		{
			"name" : "PX_CMAKE_SUPPRESS_REGENERATION",
			"properties" : 
			[
				{
					"name" : "HELPSTRING",
					"value" : "Disable zero_check projects"
				}
			],
			"type" : "BOOL",
			"value" : "OFF"
		},
		{
			"name" : "PX_COPY_EXTERNAL_DLL",
			"properties" : 
			[
				{
					"name" : "HELPSTRING",
					"value" : "Copy external dlls into SDK bin directory"
				}
			],
			"type" : "BOOL",
			"value" : "OFF"
		},
		{
			"name" : "PX_EXE_OUTPUT_DIRECTORY_CHECKED",
			"properties" : 
			[
				{
					"name" : "HELPSTRING",
					"value" : "Directory to put checked exes in"
				}
			],
			"type" : "INTERNAL",
			"value" : "C:/Users/b6024306/source/Group Work/weird-golf-game/out/build/x64-Debug/externals/physx/bin/win.x86_64.vc142.md/checked"
		},
		{
			"name" : "PX_EXE_OUTPUT_DIRECTORY_DEBUG",
			"properties" : 
			[
				{
					"name" : "HELPSTRING",
					"value" : "Directory to put debug exes in"
				}
			],
			"type" : "INTERNAL",
			"value" : "C:/Users/b6024306/source/Group Work/weird-golf-game/out/build/x64-Debug/externals/physx/bin/win.x86_64.vc142.md/debug"
		},
		{
			"name" : "PX_EXE_OUTPUT_DIRECTORY_PROFILE",
			"properties" : 
			[
				{
					"name" : "HELPSTRING",
					"value" : "Directory to put profile exes in"
				}
			],
			"type" : "INTERNAL",
			"value" : "C:/Users/b6024306/source/Group Work/weird-golf-game/out/build/x64-Debug/externals/physx/bin/win.x86_64.vc142.md/profile"
		},
		{
			"name" : "PX_EXE_OUTPUT_DIRECTORY_RELEASE",
			"properties" : 
			[
				{
					"name" : "HELPSTRING",
					"value" : "Directory to put release exes in"
				}
			],
			"type" : "INTERNAL",
			"value" : "C:/Users/b6024306/source/Group Work/weird-golf-game/out/build/x64-Debug/externals/physx/bin/win.x86_64.vc142.md/release"
		},
		{
			"name" : "PX_EXPORT_LOWLEVEL_PDB",
			"properties" : 
			[
				{
					"name" : "HELPSTRING",
					"value" : "Export low level pdb's"
				}
			],
			"type" : "BOOL",
			"value" : "OFF"
		},
		{
			"name" : "PX_FLOAT_POINT_PRECISE_MATH",
			"properties" : 
			[
				{
					"name" : "HELPSTRING",
					"value" : "Float point precise math"
				}
			],
			"type" : "BOOL",
			"value" : "OFF"
		},
		{
			"name" : "PX_GENERATE_STATIC_LIBRARIES",
			"properties" : 
			[
				{
					"name" : "HELPSTRING",
					"value" : "Generate static libraries"
				}
			],
			"type" : "BOOL",
			"value" : "OFF"
		},
		{
			"name" : "PX_ROOT_EXE_DIR",
			"properties" : 
			[
				{
					"name" : "HELPSTRING",
					"value" : "Relative root dir of the exe output directory"
				}
			],
			"type" : "INTERNAL",
			"value" : "bin/win.x86_64.vc142.md"
		},
		{
			"name" : "PX_ROOT_LIB_DIR",
			"properties" : 
			[
				{
					"name" : "HELPSTRING",
					"value" : "Relative root of the lib output directory"
				}
			],
			"type" : "INTERNAL",
			"value" : "bin/win.x86_64.vc142.md"
		},
		{
			"name" : "PX_SCALAR_MATH",
			"properties" : 
			[
				{
					"name" : "HELPSTRING",
					"value" : "Disable SIMD math"
				}
			],
			"type" : "BOOL",
			"value" : "OFF"
		},
		{
			"name" : "PX_USE_NVTX",
			"properties" : 
			[
				{
					"name" : "HELPSTRING",
					"value" : "Enabled NVTX profiling"
				}
			],
			"type" : "BOOL",
			"value" : "OFF"
		},
		{
			"name" : "PhysXCharacterKinematic_LIB_DEPENDS",
			"properties" : 
			[
				{
					"name" : "HELPSTRING",
					"value" : "Dependencies for the target"
				}
			],
			"type" : "STATIC",
			"value" : "general;PhysXFoundation;"
		},
		{
			"name" : "PhysXCommon_LIB_DEPENDS",
			"properties" : 
			[
				{
					"name" : "HELPSTRING",
					"value" : "Dependencies for the target"
				}
			],
			"type" : "STATIC",
			"value" : "general;PhysXFoundation;"
		},
		{
			"name" : "PhysXCooking_LIB_DEPENDS",
			"properties" : 
			[
				{
					"name" : "HELPSTRING",
					"value" : "Dependencies for the target"
				}
			],
			"type" : "STATIC",
			"value" : "general;PhysXCommon;general;PhysXFoundation;"
		},
		{
			"name" : "PhysXExtensions_LIB_DEPENDS",
			"properties" : 
			[
				{
					"name" : "HELPSTRING",
					"value" : "Dependencies for the target"
				}
			],
			"type" : "STATIC",
			"value" : "general;PhysXFoundation;general;PhysXPvdSDK;general;PhysX;"
		},
		{
			"name" : "PhysXPvdSDK_LIB_DEPENDS",
			"properties" : 
			[
				{
					"name" : "HELPSTRING",
					"value" : "Dependencies for the target"
				}
			],
			"type" : "STATIC",
			"value" : "general;PhysXFoundation;"
		},
		{
			"name" : "PhysXSDK_BINARY_DIR",
			"properties" : 
			[
				{
					"name" : "HELPSTRING",
					"value" : "Value Computed by CMake"
				}
			],
			"type" : "STATIC",
			"value" : "C:/Users/b6024306/source/Group Work/weird-golf-game/out/build/x64-Debug/externals/physx"
		},
		{
			"name" : "PhysXSDK_SOURCE_DIR",
			"properties" : 
			[
				{
					"name" : "HELPSTRING",
					"value" : "Value Computed by CMake"
				}
			],
			"type" : "STATIC",
			"value" : "C:/Users/b6024306/source/Group Work/weird-golf-game/submodules/PhysX/PhysX/compiler/public"
		},
		{
			"name" : "PhysXVehicle_LIB_DEPENDS",
			"properties" : 
			[
				{
					"name" : "HELPSTRING",
					"value" : "Dependencies for the target"
				}
			],
			"type" : "STATIC",
			"value" : "general;PhysXFoundation;general;PhysXPvdSDK;"
		},
		{
			"name" : "PhysX_BINARY_DIR",
			"properties" : 
			[
				{
					"name" : "HELPSTRING",
					"value" : "Value Computed by CMake"
				}
			],
			"type" : "STATIC",
			"value" : "C:/Users/b6024306/source/Group Work/weird-golf-game/out/build/x64-Debug/externals/physx/sdk_source_bin"
		},
		{
			"name" : "PhysX_LIB_DEPENDS",
			"properties" : 
			[
				{
					"name" : "HELPSTRING",
					"value" : "Dependencies for the target"
				}
			],
			"type" : "STATIC",
			"value" : "general;LowLevel;general;LowLevelAABB;general;LowLevelDynamics;general;PhysXTask;general;SceneQuery;general;SimulationController;general;PhysXPvdSDK;general;PhysXCommon;general;PhysXFoundation;"
		},
		{
			"name" : "PhysX_SOURCE_DIR",
			"properties" : 
			[
				{
					"name" : "HELPSTRING",
					"value" : "Value Computed by CMake"
				}
			],
			"type" : "STATIC",
			"value" : "C:/Users/b6024306/source/Group Work/weird-golf-game/submodules/PhysX/PhysX/source/compiler/cmake"
		},
		{
			"name" : "SPDLOG_BUILD_BENCH",
			"properties" : 
			[
				{
					"name" : "HELPSTRING",
					"value" : "Build benchmarks (Requires https://github.com/google/benchmark.git to be installed)"
				}
			],
			"type" : "BOOL",
			"value" : "OFF"
		},
		{
			"name" : "SPDLOG_BUILD_EXAMPLE",
			"properties" : 
			[
				{
					"name" : "HELPSTRING",
					"value" : "Build example"
				}
			],
			"type" : "BOOL",
			"value" : "OFF"
		},
		{
			"name" : "SPDLOG_BUILD_EXAMPLE_HO",
			"properties" : 
			[
				{
					"name" : "HELPSTRING",
					"value" : "Build header only example"
				}
			],
			"type" : "BOOL",
			"value" : "OFF"
		},
		{
			"name" : "SPDLOG_BUILD_TESTS",
			"properties" : 
			[
				{
					"name" : "HELPSTRING",
					"value" : "Build tests"
				}
			],
			"type" : "BOOL",
			"value" : "OFF"
		},
		{
			"name" : "SPDLOG_BUILD_TESTS_HO",
			"properties" : 
			[
				{
					"name" : "HELPSTRING",
					"value" : "Build tests using the header only version"
				}
			],
			"type" : "BOOL",
			"value" : "OFF"
		},
		{
			"name" : "SPDLOG_FMT_EXTERNAL",
			"properties" : 
			[
				{
					"name" : "HELPSTRING",
					"value" : "Use external fmt library instead of bundled"
				}
			],
			"type" : "BOOL",
			"value" : "OFF"
		},
		{
			"name" : "SPDLOG_FMT_EXTERNAL_HO",
			"properties" : 
			[
				{
					"name" : "HELPSTRING",
					"value" : "Use external fmt header-only library instead of bundled"
				}
			],
			"type" : "BOOL",
			"value" : "OFF"
		},
		{
			"name" : "SPDLOG_INSTALL",
			"properties" : 
			[
				{
					"name" : "HELPSTRING",
					"value" : "Generate the install target"
				}
			],
			"type" : "BOOL",
			"value" : "OFF"
		},
		{
			"name" : "SPDLOG_NO_ATOMIC_LEVELS",
			"properties" : 
			[
				{
					"name" : "HELPSTRING",
					"value" : "prevent spdlog from using of std::atomic log levels (use only if your code never modifies log levels concurrently"
				}
			],
			"type" : "BOOL",
			"value" : "OFF"
		},
		{
			"name" : "SPDLOG_NO_EXCEPTIONS",
			"properties" : 
			[
				{
					"name" : "HELPSTRING",
					"value" : "Compile with -fno-exceptions. Call abort() on any spdlog exceptions"
				}
			],
			"type" : "BOOL",
			"value" : "OFF"
		},
		{
			"name" : "SPDLOG_NO_THREAD_ID",
			"properties" : 
			[
				{
					"name" : "HELPSTRING",
					"value" : "prevent spdlog from querying the thread id on each log call if thread id is not needed"
				}
			],
			"type" : "BOOL",
			"value" : "OFF"
		},
		{
			"name" : "SPDLOG_NO_TLS",
			"properties" : 
			[
				{
					"name" : "HELPSTRING",
					"value" : "prevent spdlog from using thread local storage"
				}
			],
			"type" : "BOOL",
			"value" : "OFF"
		},
		{
			"name" : "SPDLOG_PREVENT_CHILD_FD",
			"properties" : 
			[
				{
					"name" : "HELPSTRING",
					"value" : "Prevent from child processes to inherit log file descriptors"
				}
			],
			"type" : "BOOL",
			"value" : "OFF"
		},
		{
			"name" : "SPDLOG_SANITIZE_ADDRESS",
			"properties" : 
			[
				{
					"name" : "HELPSTRING",
					"value" : "Enable address sanitizer in tests"
				}
			],
			"type" : "BOOL",
			"value" : "OFF"
		},
		{
			"name" : "SPDLOG_WCHAR_FILENAMES",
			"properties" : 
			[
				{
					"name" : "HELPSTRING",
					"value" : "Support wchar filenames"
				}
			],
			"type" : "BOOL",
			"value" : "OFF"
		},
		{
			"name" : "SPDLOG_WCHAR_SUPPORT",
			"properties" : 
			[
				{
					"name" : "HELPSTRING",
					"value" : "Support wchar api"
				}
			],
			"type" : "BOOL",
			"value" : "OFF"
		},
		{
			"name" : "WINCRT_DEBUG",
			"properties" : 
			[
				{
					"name" : "HELPSTRING",
					"value" : "Windows CRT build setting"
				}
			],
			"type" : "INTERNAL",
			"value" : "/MDd /D \"_DEBUG\""
		},
		{
			"name" : "_GNUInstallDirs_LAST_CMAKE_INSTALL_PREFIX",
			"properties" : 
			[
				{
					"name" : "HELPSTRING",
					"value" : "CMAKE_INSTALL_PREFIX during last run"
				}
			],
			"type" : "INTERNAL",
			"value" : "C:/Users/b6024306/source/Group Work/weird-golf-game/out/install/x64-Debug"
		},
		{
			"name" : "enet_BINARY_DIR",
			"properties" : 
			[
				{
					"name" : "HELPSTRING",
					"value" : "Value Computed by CMake"
				}
			],
			"type" : "STATIC",
			"value" : "C:/Users/b6024306/source/Group Work/weird-golf-game/out/build/x64-Debug/submodules/enet"
		},
		{
			"name" : "enet_SOURCE_DIR",
			"properties" : 
			[
				{
					"name" : "HELPSTRING",
					"value" : "Value Computed by CMake"
				}
			],
			"type" : "STATIC",
			"value" : "C:/Users/b6024306/source/Group Work/weird-golf-game/submodules/enet"
		},
		{
			"name" : "spdlog_BINARY_DIR",
			"properties" : 
			[
				{
					"name" : "HELPSTRING",
					"value" : "Value Computed by CMake"
				}
			],
			"type" : "STATIC",
			"value" : "C:/Users/b6024306/source/Group Work/weird-golf-game/out/build/x64-Debug/submodules/spdlog"
		},
		{
			"name" : "spdlog_SOURCE_DIR",
			"properties" : 
			[
				{
					"name" : "HELPSTRING",
					"value" : "Value Computed by CMake"
				}
			],
			"type" : "STATIC",
			"value" : "C:/Users/b6024306/source/Group Work/weird-golf-game/submodules/spdlog"
		},
		{
			"name" : "weird_golf_game_BINARY_DIR",
			"properties" : 
			[
				{
					"name" : "HELPSTRING",
					"value" : "Value Computed by CMake"
				}
			],
			"type" : "STATIC",
			"value" : "C:/Users/b6024306/source/Group Work/weird-golf-game/out/build/x64-Debug"
		},
		{
			"name" : "weird_golf_game_SOURCE_DIR",
			"properties" : 
			[
				{
					"name" : "HELPSTRING",
					"value" : "Value Computed by CMake"
				}
			],
			"type" : "STATIC",
			"value" : "C:/Users/b6024306/source/Group Work/weird-golf-game"
		}
	],
	"kind" : "cache",
	"version" : 
	{
		"major" : 2,
		"minor" : 0
	}
}
